{"丫钯":"1.叉草用的农具。","丫叉":"1.交叉。","丫槎":"1.丫杈，植物的枝丫。","丫铲":"1.丫形铲子。","丫蛋":"1.方言。指女该。","丫裆":"1.指人体两股之间的地方。","丫儿":"1.一种似钌铞儿的扣子。","丫环":"1.同\"丫鬟\"。 \n2.犹言劳驾。","丫髻":"1.谓梳着丫形发髻。 \n2.指丫形发髻。 \n3.借指童仆。 \n4.荔枝品种之一。","丫角":"1.丫髻。小孩的发式。 \n2.借指童仆。 \n3.借指处女。","丫戾":"1.盘曲成叉形。戾，捩。","丫路":"1.叉路。","丫木":"1.上端分叉的木头。","丫雀":"1.喜鹊的别称。","丫童":"1.挽着丫髻的儿童。","丫头":"①女孩子花面丫头十三四，春来绰约向人时。②婢女。参见丫鬟”。","丫头片子":"1.方言。对女孩子的戏称。","丫嬛":"1.丫鬟，婢女。","丫丫":"1.两髻分叉的形状。 \n2.指女孩。 \n3.象声词。","丫丫叉叉":"1.枝丫杂乱交叉的样子。","丫枝":"1.枝桠。","丫子":"1.物体分叉的地方。 \n2.方言称脚为脚丫子，省称丫子。"}