{"予齿去角":"1.谓天生动物赋予齿就不赋予角。比喻事物无十全十美。","予冲人":"1.见\"予冲人\"。","予冲子":"1.即予冲人。","予赐":"1.予告和赐告。","予夺":"1.赐予和剥夺。 \n2.引申为赏罚。 \n3.裁决，裁夺。 \n4.褒贬。","予夺生杀":"1.《周礼．天官﹑大宰》的\"八柄\"中有予﹑夺﹑生﹑诛(责备)等权力◇因以\"予夺生杀\"泛指帝王掌握的赏罚生死大权。","予告":"1.汉代二千石以上有功官员依例给以在官休假的待遇，谓之予告。告，休假。 \n2.后代凡大臣因病﹑老准予休假或退休的都叫予告。","予勾":"1.亦作\"予句\"。 \n2.谓皇帝或其指定的大臣用朱笔在判处死刑者的名字上画勾以示批准。","予归":"1.准予辞官回家。","予句":"1.见\"予勾\"。","予决":"1.给予决定或裁决。","予乐":"1.指汉明帝永平三年所用的郊庙音乐《大予乐》。","予美":"1.指自己所爱的人。","予末小子":"1.古代帝王对先王或长辈的自称。 \n2.常人对先辈﹑长者的自称。","予宁":"1.给丧假。","予取予求":"1.从我处取求。 \n2.引申为任意索取。 \n3.犹言随心所欲。","予取予携":"1.亦作\"予取予夺\"。 \n2.从我处掠取。","予圣":"1.自以为圣人，谓自夸高明。","予违汝弼":"1.古代天子勖勉大臣进谏之词。言我有过失，你应匡正。","予小子":"1.古代帝王对先王或长辈的自称。《书．泰誓上》\"肆予小子发﹐以尔友邦冢君﹐观政于商。\"《诗．周颂．闵予小子》\"闵予小子﹐遭家不造。\"又为天子居丧时的自称。 \n2.常人对先辈﹑长者的自称。","予雄":"1.自谓英雄。","予一人":"1.古代帝王的自称。","予以":"1.给以。","予知":"1.自谓聪明。","予智予雄":"1.自以为聪明和英雄。形容妄自尊大。","予取予夺":"从我处掠取。"}