{"击梆":"1.敲打梆子。用以宣告集散﹑表示有事申报或巡更示警等。","击崩":"1.攻击崩溃的敌人。","击毙":"打死（多指用枪）。","击髀":"1.以手拍股。","击鞭锤镫":"1.谓驱马疾行。指急行军。","击剥":"1.谓以严刑峻法虐民。","击钵":"1.见\"击钵催诗\"。","击钵催诗":"1.南朝齐竟陵王萧子良﹐常于夜间邀集才人学士饮酒赋诗﹐刻烛限时﹐规定烛燃一寸﹐诗成四韵。萧文琰认为这并非难事﹐乃与丘令楷﹑江洪二人改为击铜钵催诗﹐要求钵声一止﹐诗即吟成。见《南史．王僧孺传》◇以\"击钵催诗\"指限时成诗﹐亦以喻诗才敏捷。","击博":"1.古代一种游戏。","击搏挽裂":"1.攻打撕裂。形容争斗激烈。","击馋":"1.卖熟食者所敲的一种小木梆。","击笞":"1.鞭笞示罚。","击冲":"1.撞击。","击触":"1.相打;碰撞。","击穿":"电介质在强电场作用下丧失原有绝缘性质的现象。固体电介质击穿后，会出现熔化或烧焦的通道，或出现机械损伤的裂纹；气体和液体电介质击穿时会出现电火花。发生击穿的电压值与材料的种类、厚度及使用时的温度、压力等因素有关。","击床":"1.击杀于床上。","击辝":"1.车轴头相碰。形容宾客车辆之多。","击刺":"1.用戈矛劈刺。 \n2.引申为攻伐﹐诛杀。 \n3.谓击刺之术。","击打":"1.打击;拍打。","击点":"1.打铜点(小锣)报时。","击电奔星":"1.形容快速。","击刁":"1.敲打刁斗。","击动":"1.打动。","击断":"1.打断。 \n2.专断;决断。 \n3.果敢坚决。","击分":"1.犹激忿。击﹐用同\"激\"。","击缶":"1.亦作\"击缻\"。 \n2.敲击瓦缶。古人或以缶为乐器﹐用以打拍子。缶﹐瓦盆。","击拂":"1.拍击;拍打。 \n2.布茶时的一种手法。","击箙":"1.敲箭袋。契丹俗，在皇室再生仪里所举行的一种仪式。","击拊":"1.见\"击石拊石\"。","击菒":"1.掠去枯草。","击革":"1.击鼓。","击攻":"1.攻击。","击毂摩肩":"1.形容车马众多。语出《战国策．齐策一》\"临淄之涂﹐车毂击﹐人肩摩。\"","击谷":"1.鸟名。即布谷。","击鼓传花":"1.见\"击鼓催花\"。","击鼓催花":"1.唐南卓《羯鼓录》\"上(唐明皇)洞晓音律……尤爱羯鼓玉笛﹐常云八音之领袖﹐诸乐不可为比。尝遇二月初﹐诘旦﹐巾栉方毕﹐时当宿雨初晴﹐景色明丽﹐小殿内庭﹐柳杏将吐。睹而叹曰'对此景物﹐岂得不为他判断之乎？'左右相目﹐将命备酒﹐独高力士遣取羯鼓。上旋命之﹐临轩纵击一曲﹐曲名《春光好》。神思自得。及顾柳杏﹐皆已发拆。上指而笑谓嫔御曰'此一事不唤我作天公﹐可乎？'\"后用作酒令。鼓响传花﹐声止﹐持花未传者即须饮酒。今亦用作游戏。","击攌":"1.谓敲打金石和按捺箫管等乐器。指奏乐。","击毁":"击中并摧毁～敌方坦克三辆ㄧ建筑物被雷电～。","击楫":"敲拍船桨。《晋书·祖逖传》记载祖逖带兵北伐时，渡江到中流，他击楫立誓说祖逖不能清中原而复济者，有如大江。”后来用击楫”或击楫中流”表示慷慨激昂的报国壮志长江不限天南北，击楫中流看誓师。","击楫誓":"1.见\"击楫中流\"。","击戛":"1.敲打。语本《书．益稷》\"戛击鸣球﹐搏拊琴瑟以咏。\"","击奸":"1.弹劾奸臣。","击剑运动":"两人手持特制钢剑以刺劈动作进行格斗的一种体育运动。比赛项目男子有花剑、重剑、佩剑；女子仅有花剑。花剑、重剑进攻时只准刺，佩剑还可劈打。男子比赛每场6分钟打五剑；女子每场5分钟打四剑。按刺和劈中对手身体有效部位次数的多少定胜负。","击角歌":"1.扣角歌。","击节":"打拍子，表示得意或赞赏～叹赏（形容对诗文、音乐等的赞赏）。","击竞":"1.犹竞争。","击镜":"1.古代迷信习俗。日月食时﹐诸侯夫人敲打镜子以救。","击咎":"1.古代称土星散变后的天体之一。","击掬":"1.见\"击鞠\"。","击踘":"1.见\"击鞠\"。","击决":"1.迅速作出决定。","击均":"1.攻击与己势均力敌的敌人。","击考":"1.敲击。","击叩":"1.《礼记．学记》\"善待问者如撞钟﹐叩之以小者则小鸣﹐叩之以大者则大鸣﹐待其从容﹐然后尽其声。\"孔颖达疏\"从读为舂者﹐舂谓击也﹐以为声之形容。言钟之为体﹐必待其击﹐每一舂而为一容﹐然后尽其声。善答者亦待其一问﹐然后一答﹐乃尽说义理也。\"后因以\"击叩\"喻发问求解。 \n2.见\"击扣\"。","击扣":"1.轻轻敲打。比喻督促。","击戾":"1.抵触;乖忤。","击落":"打下来（天空的飞机等）。","击落地球":"网球运动技术名词。指击落地一次后的球。有正拍和反拍击球。可击直线、斜线或挑高球、放短球等种，也可用劈击使球垂直下旋，用削击使球侧旋，用提拉使球上旋。","击马":"1.在摴蒲戏中打去敌子。","击蒙":"1.发蒙;启蒙。","击绵":"1.见\"击絮\"。","击灭":"1.打击消灭。","击目":"1.目击﹐目睹。","击难":"1.批评;指责。","击瓯":"1.瓯﹐盛水或酒的陶瓷器。古人也用为乐器﹐盛水击之以和乐拍◇世演变至可单独奏乐。","击排":"1.攻击排斥。","击排冒没":"1.谓攻击排斥﹐轻率而不顾一切。","击抨":"1.抨击﹐批评指责。","击搒":"1.打击搒掠。","击披":"1.劈击﹐打散。","击掊":"1.击倒。","击扑":"1.扑打。","击其不意":"1.在敌人没有预料到的情况下进行攻击。","击切":"1.犹切合。","击琴":"1.琴名。用竹敲击琴弦发声﹐异于用指弹的琴。 \n2.敲琴。","击球":"1.同\"击鞠\"。","击壤":"古代一种投掷游戏。壤”为前广后锐的木板，长1尺4寸，阔3寸，形如屐。游戏时先侧一壤于地，在距三、四十步处以手中壤击之，中者为胜。为尧时老年人盛行的娱乐活动。","击壤鼓腹":"1.《庄子．马蹄》\"夫赫胥氏之时﹐民居不知所为﹐行不知所之﹐含哺而熙﹐鼓腹而游。\"《艺文类聚》卷十一引晋皇甫谧《帝王世纪》\"﹝帝尧之世﹞天下大和﹐百姓无事﹐有五十老人击壤于道。\"原谓人民吃得饱﹐有馀闲游戏◇用为称颂太平盛世之典。","击赏":"〈书〉击节称赏；赞赏。","击射":"1.射击。","击石波":"1.书法术语名。章草及章程﹑行押等用之。用笔直过。","击石弹丝":"1.谓奏乐。","击石拊石":"1.敲打石磬。","击手":"1.拍掌。","击碎唾壶":"1.《晋书．王敦传》\"﹝王敦﹞每酒后辄咏魏武帝乐府歌曰'老骥伏枥﹐志在千里。烈士暮年﹐壮心不已。'以如意打唾壶为节﹐壶边尽缺。\"原形容对文学作品的极度赞赏﹐后亦用以形容抒发壮怀或不平之情。","击汰":"1.拍击水波。亦指划船。","击托":"1.捣毁;推倒。","击柝":"1.亦作\"击\"。亦作\"击\"。 \n2.敲梆子巡夜。亦喻战事﹐战乱。","击唾壶":"1.见\"击碎唾壶\"。","击丸":"1.古时的一种杂技表演。亦指这种杂技的表演者。","击危":"1.犹违碍。","击瓮图":"1.描绘宋司马光幼时打破水瓮拯救儿童故事的图画。","击瑕":"1.攻击敌人布防疏漏之处。","击鲜":"1.宰杀活的牲畜禽鱼﹐充作美食。","击虚":"1.乘敌之空虚而进攻。","击絮":"1.捶击绵絮『袁康《越绝书．荆平王内传》\"子胥遂行﹐至溧阳界中﹐见一女子﹐击絮于濑水之中。子胥曰'岂可得托食乎？'女子曰'诺。'即发箪饭﹐清其壶浆而食之。子胥食已而去﹐谓女子曰'掩尔壶浆﹐毋令之露。'女子曰'诺。'子胥行五步﹐还顾﹐女子自纵于濑水之中而死。\"汉赵晔《吴越春秋．王僚使公子光传》作\"击绵\"◇用以为典实。","击衣":"1.春秋末晋人豫让事智伯﹐智伯甚尊宠之。及智伯为赵襄子等所灭﹐豫让立志必为报仇而死﹐以报智伯。乃变名姓为刑人﹐又漆身为厉﹐吞炭为哑﹐两次行刺赵襄子﹐未成而自杀。自杀前﹐要求赵襄子给衣服而击之﹐以示报仇之意。\"襄子大义之﹐乃使使持衣与豫让。豫让拔剑三跃而击之﹐曰'吾可以下报智伯矣！'\"事见《史记．刺客列传》◇因以\"击衣\"为报仇的典实。","击应":"1.战斗中各部队受到攻击时互相接应。语本《孙子．九地》\"率然者﹐常山之蛇也﹐击其首则尾至﹐击其尾则首至﹐击其中则首尾俱至。\"","击玉壶":"1.见\"击碎唾壶\"。","击辕":"1.谓敲打车辕中乐成声。","击越":"1.谓雷霆下击。 \n2.激越。形容声音激扬清越。","击贼笏":"1.唐德宗时﹐朱泚谋反﹐召段秀实议事﹐秀实以笏击泚﹐大骂﹐被杀。见《新唐书．段秀实传》◇以\"击贼笏\"为称颂忠贞或正气凛然的典实。","击轧":"1.相触﹐碰撞。","击斩":"1.斩杀。","击掌":"①拍手～称好ㄧ～为号。②双方相互拍击手掌，表示对所立誓言，永不反悔～为盟。","击杖":"1.古代迷信习俗。日月食时﹐大夫之妻敲打棒杖以救。","击棹":"1.打桨。谓驾船。","击折":"1.打断。","击征":"1.鹰的别名。","击钟":"1.见\"击钟\"。","击钟鼎食":"1.打钟列鼎而食。形容贵族或富人生活奢华。","击钟食":"1.见\"击钟鼎食\"。","击竹":"1.用两片竹板击打成节拍以合歌﹐犹今快板所用。","击柱":"1.刺柱。《汉书．叔孙通传》\"群臣饮，争功，醉或妄呼，拔剑击柱。\"南朝梁江淹《恨赋》\"拔剑击柱，吊影惭魂。\"后亦用以指臣下争功无礼。","击筑人":"1.喻慷慨悲歌之士。","击撞":"1.叩打。亦喻声韵铿锵。 \n2.犹打击﹐攻讦。","击卒":"1.谓辰星(水星)当出现而不出现。","击":"1.见\"击柝\"。","击鼓鸣金":"古时两军作战时用鼓和金发号施令，击鼓则进，鸣金则退。","击楫中流":"比喻立志奋发图强。","击节称赏":"节节拍；赏赞赏。形容对诗文、音乐等的赞赏。","击节叹赏":"节节拍；赏赞赏。形容对诗文、音乐等的赞赏。","击玉敲金":"如金玉被撞击而发出的声音。形容言辞铿然有声，正确无误。","击中要害":"要害易于致命的部位，引伸为重要部门或问题的关键。正打中致命的部位。","击钟陈鼎":"钟古代乐器；鼎古代炊器。击钟列鼎而食。形容贵族的豪华排场。","击筑悲歌":"击敲击；筑古乐器名。敲击着筑，唱着悲壮的歌。形容慷慨悲歌。"}