{"厉兵":"1.磨砺兵器，使锋利。","厉兵秣马":"见〖秣马厉兵〗。","厉兵粟马":"1.磨快兵器喂饱马。指准备作战。","厉操":"1.砥砺节操。","厉诚":"1.激励忠诚。","厉饬":"1.见\"厉饰\"。","厉崇":"1.勉励推重。","厉毒":"1.疠毒，瘟疫的毒气。","厉度":"1.涉水而过。","厉风":"1.大风;烈风。 \n2.指西北风。 \n3.喻以高尚的行为激励影响。","厉服":"1.服猛厉之服，穿戎装。","厉抚":"1.勉励抚慰。","厉高":"1.极高貌。","厉鬼":"恶鬼；鬼怪。","厉疾":"1.迅猛。 \n2.灾疫。","厉阶":"1.祸端。","厉揭":"1.涉水。连衣涉水叫厉，提起衣服涉水叫揭。语出《诗．邶风．匏有苦叶》\"深则厉，浅则揭。\"毛传\"以衣涉水为厉，谓由带以上也。揭，褰衣也。\" \n2.指所受影响深浅不同。","厉节":"1.厉，也写作\"励\"。激励节操。","厉禁":"1.遮挡，禁止。谓设卫警戒，限制出入。 \n2.严禁;禁令。","厉精":"1.振奋精神。","厉精更始":"1.振奋精神，从事革新。","厉精图治":"1.振奋精神，力图治理好国家。","厉精为治":"1.振奋精神，治理好国家。","厉厉":"1.形容憎恨。 \n2.寒风猛烈貌。","厉怜王":"1.麻疯病人怜悯被劫杀的君主，认为比自己还可怜。厉，麻疯病。","厉民":"1.训练人民。 \n2.虐害人民。","厉虐":"1.暴虐。 \n2.妖孽。","厉气":"1.鼓励斗志。 \n2.邪恶之气;瘟疫之气。 \n3.严厉的神色。","厉然":"1.形容严肃;严格。","厉色":"严厉的面色；愤怒的表情正言～。","厉山氏":"1.即炎帝神农。","厉涉":"1.连衣涉水。","厉身":"1.磨砺自身。","厉神":"1.大神。","厉世":"1.激励世人。","厉世摩钝":"1.亦作\"厉世磨钝\"。 \n2.激励世人，使鲁钝的人奋发有为。","厉饰":"1.亦作\"厉饬\"。 \n2.戎装，军服。一说，佩猛厉之饰物。","厉爽":"1.犹伤害。","厉俗":"1.激励世俗。","厉肃":"1.严肃。","厉祟":"1.为害作祟。","厉坛":"1.祭无祀鬼神的坛。","厉武":"1.振奋武备。","厉骛":"1.疾驰。","厉响":"1.激出音响。","厉心":"1.专心;用心。","厉行":"严格实行～节约。","厉言":"1.声色严厉地说话。","厉妖":"1.邪恶怪异之物。","厉疫":"1.即疠疫，急性传染病。","厉翼":"1.厉，也写作\"励\"。奋勉辅佐。","厉音":"1.声音严厉。","厉直":"1.严肃正直。","厉志":"1.激励意志;磨练意志。","厉鸷":"1.勇猛。","厉浊激贪":"1.谓激励行秽心贪之世人。","厉行节约":"厉严格。严格地实行节约。"}