{"响板":"1.见\"响版\"。","响版":"1.亦作\"响板\"。 \n2.乐器。以石制成，寺观或家中设于殿前堂上作传呼之用。","响报":"1.谓应报之速如回声。","响抃":"1.击掌作声以示热烈响应。","响卜":"1.旧时迷信，据说听别人讲话可卜吉凶，谓之\"响卜\"。一般在除夕夜进行。","响钞":"1.元代发行纸币，称为钞，故俗称现银和铜钱为\"响钞\"。","响钞精银":"1.成色高的银子。","响彻云表":"1.见\"响彻云霄\"。","响彻云际":"1.见\"响彻云霄\"。","响彻云霄":"1.形容声音响亮高昂，能穿透云层。","响铛铛":"1.见\"响珰珰\"。","响答":"1.响应;应答。","响答影随":"1.如应声和答﹑形影相随。比喻两者紧密相连。","响珰珰":"1.亦作\"响铛铛\"。亦作\"响当当\"。 \n2.形容敲打的声音响亮。 \n3.比喻有名气或出色﹑过硬。","响动":"1.响声振动。 \n2.动静;声响。 \n3.指奏乐。","响黩":"1.名声污浊。","响度":"人耳感觉到的声音强弱的程度。乐音的特性之一。与声强和频率等有关。当声强增大时响度也增大，反之亦然。","响遏行云":"遏阻挡。响亮的声音高入云霄，阻挡住飘流的云彩。形容歌声响亮抚节悲歌，声振林木，响遏行云。","响坟":"1.回教信徒对传说中唐时粤东伊斯兰教教主墓的称呼。","响附":"1.响应归附。","响赴":"1.响应奔赴。","响瓜儿":"1.用手打人脑瓜子作响声。","响骇":"1.犹震惊。","响合":"1.乐声谐和。比喻相处和睦。 \n2.响应聚合。","响和":"1.应声相和。","响和景从":"1.见\"响答影随\"。","响胡芦":"1.亦作\"响葫芦\"。 \n2.玩具名。口吹时声如\"不登\"，故亦谓之\"不镫\"。","响葫芦":"1.见\"响胡芦\"。","响环":"1.乐器名。","响豁":"1.犹言财运亨通。","响集":"1.响应聚集。","响箭":"1.即鸣镝。古称嚆矢。射时发出响声的箭。","响景":"1.回声和日影。比喻反应迅速。","响寇":"1.即响马。","响廊":"1.即响屧廊。","响朗":"1.犹响亮。","响老":"1.清代农民军\"捻子\"(捻军前身)首领的称谓。","响冷冷":"1.形容清脆的响声。","响亮":"1.声音清晰洪亮。 \n2.形容诗文声调朗畅。 \n3.大的响声。 \n4.比喻名声好，声誉高。","响喨":"1.大的声响。","响马":"古指拦路抢劫的强盗。因抢劫前先放出响箭而得名这带常有响马出没。","响慕":"1.向往，仰慕。","响捻子":"1.清代农民军\"捻子\"首领的称谓。","响器":"1.铙﹑钹﹑锣﹑鼓等打击乐器的统称。","响晴":"1.犹言晴朗高爽。","响泉":"1.古琴名。","响珊珊":"1.形容沙沙的轻响声。","响声":"1.声音。","响石":"1.击以发声的石器。 \n2.巨石名。在今江西省南丰县城东。","响榻":"1.响拓。榻，用同\"搨\"。","响糖狮子":"1.食品名。","响铁":"1.精炼的铁。亦指用以敲击发响的精铁。","响铜":"1.一种合金。由铜﹑铅﹑锡按一定比例混合炼成。可制乐器。","响头":"1.磕头时额头触地作声，称为\"响头\"。 \n2.指头部与他物相撞发声。","响拓":"1.见\"响拓\"。","响尾蛇":"爬行纲，蝰科。生活在美洲大陆的一种毒蛇。体长可达2米。身体黄绿色，有黑褐色菱形斑纹。尾端有角质环，摆动时会发出响声，故名。眼和鼻孔间有颊窝，能测知周围温血动物的位置。以野兔和鼠类为食，也吃小鸟、蜥蜴等。","响犀":"1.犀牛角所制的棒槌，击物能应声回响。","响象":"1.同\"响像\"。","响像":"1.依稀;隐约。 \n2.声音容貌。常指死者。","响效":"1.犹响应。","响屧":"1.指女子的步履声。","响屧廊":"1.春秋时吴王宫中的廊名。遗址在今江苏省苏州市西灵岩山。","响杨":"1.落叶乔木。幼树树皮光滑，青白色。老树树皮有裂沟。叶子卵形或三角状卵形，边缘的波状的齿。木材白色，可供建筑，也用来造船﹑制纸等。","响洋":"1.旧时银元的俗称。","响逸":"1.音响悠扬。 \n2.比喻文气奔放。","响音":"1.语音学上指元音(如a﹑e﹑o)和乐音成分占优势的辅音(如m，n，l)。有时专指乐音成分占优势的辅音。","响应":"回声相应。表示对某种号召或倡议应和或赞同响应号召｜天下云集而响应。","响玉":"1.碰击时能发声响的玉石。","响臻":"1.应声而至;响应归附。","响振":"1.响声振动。","响震":"1.响声震动。 \n2.惊惧;骚乱。","响字":"1.指诗词中读音响亮﹑形象鲜明的字眼。","响":"1.古乐器名。"}