{"幽蔼":"1.亦作\"幽霭\"。幽深貌。 \n2.盛貌。","幽霭":"1.见\"幽蔼\"。","幽暧":"1.幽暗;昏暗。","幽闇":"1.昏暗之中。","幽暗":"1.昏暗不明。","幽黯":"1.暗淡;阴暗。","幽奥":"1.深远;深奥。","幽抱":"1.幽独的情怀。","幽闭":"1.幽禁;禁闭。 \n2.指关闭。 \n3.古代施于女性的宫刑。","幽敝":"1.见\"幽蔽\"。","幽辟":"1.幽僻，昏暗。","幽閟":"1.犹幽深。 \n2.谓深闭。","幽碧":"1.深绿色。","幽蔽":"1.亦作\"幽敝\"。 \n2.深暗。","幽壁":"1.阴暗的墙壁。","幽变":"1.隐微的变化。","幽禀":"1.幽静的本性。","幽并":"1.幽州和并州的并称。约当今河北﹑山西北部和内蒙古﹑辽宁一部分地方。其俗尚气任侠。因借指豪侠之气。","幽并儿":"1.古代幽并二州多豪侠之士，故用以喻侠客。语出三国魏曹植《白马篇》\"借问谁家子?幽并游侠儿。\"","幽薄":"1.谓茂草丛生之处。","幽步":"1.闲步。","幽操":"1.隐逸不仕的操守。","幽草":"1.幽深地方的草丛。","幽侧":"1.隐僻鄙陋之处。","幽敞":"1.幽静宽敞。","幽沉":"1.见\"幽沈\"。","幽榇":"1.棺材。","幽城":"1.犹幽府。","幽愁":"1.忧愁;暗愁。","幽悰":"1.隐藏在内心的感情。","幽翠":"1.深绿。指葱茏的草木。","幽单":"1.犹孤独。","幽淡":"1.素净淡雅。 \n2.见\"幽澹\"。","幽澹":"1.微动的水波。 \n2.幽静，静寂。","幽觌":"1.幽静地欣赏。","幽都":"1.北方之地。 \n2.谓阴间都府。","幽独":"1.静寂孤独。亦指静寂孤独的人。 \n2.独处。","幽遯":"1.犹隐逸。","幽厄":"1.犹困厄，灾难。","幽芳":"1.清香。亦指香花。 \n2.比喻高洁的德行。","幽房":"1.深暗的房间。 \n2.墓穴。","幽放":"1.幽禁放逐。","幽废":"1.幽禁废黜。","幽纷":"1.昏乱不明。","幽芬":"1.清香。 \n2.比喻盛德美名。","幽愤":"1.郁结的怨愤。","幽否":"1.困厄。","幽伏":"1.犹隐伏。","幽府":"1.阴间地府。","幽感":"1.微妙的感应。 \n2.深沉的感慨。","幽隔":"1.远隔。 \n2.引申指人死入阴间，与世隔绝。","幽輵":"1.象声词。","幽宫":"1.深宫。 \n2.谓坟墓。","幽谷":"1.幽深的山谷。","幽怪":"1.幽灵怪物。 \n2.神秘奇怪。","幽关":"1.深邃的关隘;紧闭的关门。 \n2.道家谓两肾之间。 \n3.犹玄关。指入道之门。","幽光":"1.潜隐的光辉。常用以指人的品德。 \n2.微弱的光。","幽闺":"1.深闺。多指女子的卧室。","幽诡":"1.阴私奸诈。","幽国":"1.政治昏暗的国家。","幽合":"1.深闺。指旧时女子的卧房。","幽褐":"1.谓幽居贫困之士。","幽壑":"1.深谷;深渊。","幽恨":"1.深藏于心中的怨恨。","幽衡":"1.黑色的玉衡。幽，通\"黝\"。 \n2.借指微贱的出身。","幽蘅":"1.香草名。即蘅芜。","幽薨":"1.指王侯被囚禁而死。","幽弘":"1.深大貌。","幽后":"1.周幽王之后，指襧姒。","幽曶":"1.犹幽隐。指隐居的人。","幽嫮":"1.婉约美好。","幽怀":"1.隐藏在内心的情感。","幽欢":"1.幽会的欢乐。","幽荒":"1.荒远之地。泛指九州之外。 \n2.指隐逸之士。","幽篁":"1.指幽深的竹林。","幽会":"在幽胜的地方聚会。多指相爱的男女秘密相会密林中幽会｜雅欢幽会，良辰可惜虚抛掷。","幽晦":"1.昏暗。 \n2.不显。","幽秽":"1.草木丛生貌。","幽蕙":"1.蕙草。","幽昏":"1.亦作\"幽昬\"﹑\"幽?\"。暗昧不明。 \n2.见\"幽婚\"。","幽昬":"1.见\"幽昏\"。","幽婚":"1.亦作\"幽昏\"。 \n2.魏晋志怪小说中谓人与鬼结婚。如范阳人卢充年二十，先冬至一日出宅西猎戏，过崔少府墓，与崔氏亡女成婚三日，后生一子。见晋干宝《搜神记》卷十六◇亦指非人间配偶。","幽魂":"1.谓人死后的阴魂。","幽机":"1.犹玄机。奥妙之理。","幽迹":"1.隐微的心迹。 \n2.隐居的踪迹。","幽极":"1.指深奥的义理。","幽寂":"1.幽静﹑清静。 \n2.指文笔典雅﹑简洁。","幽蓟":"1.幽州和蓟州的并称。","幽缄":"1.密封。","幽蹇":"1.僻冷奇险。","幽荐":"1.谓祭奠死者。","幽贱":"1.微贱。","幽鉴":"1.犹玄鉴。喻微妙高深的见解。","幽键":"1.见\"幽揵\"。","幽劫":"1.谓遭囚禁，被胁制。","幽洁":"1.雅静高洁。 \n2.幽雅清静。","幽结":"1.犹郁结。","幽介":"1.卑微孤介的人。","幽襟":"1.犹幽怀。","幽禁":"1.囚禁。","幽经":"1.指《相鹤经》。传说为神仙的经书。","幽景":"1.幽静的景色。","幽径":"1.见\"幽径\"。","幽靓":"1.犹幽静。","幽境":"1.幽雅的胜境。","幽静":"深幽静寂幽静的山谷｜幽静的庭院｜一切是那么幽静、恬淡而自然，像一股清冽的泉水。","幽镜":"1.藏于匣中之镜。 \n2.喻寂静的池塘。","幽扃":"1.深锁的门户。 \n2.谓坟墓。","幽迥":"1.犹深远。","幽窘":"1.囚困。","幽柩":"1.灵柩。","幽居":"1.隐居，不出仕。 \n2.深居。 \n3.僻静的居处。 \n4.墓室。","幽娟":"1.幽静美好。","幽镌":"1.犹幽篆。","幽隽":"1.清逸﹑隽永。","幽眷":"1.深切思念。","幽絶":"1.清幽殊绝。","幽峻":"1.隐僻峻峭。亦指隐僻峻峭之处。","幽浚":"1.犹深远。","幽垲":"1.幽静高爽。","幽坎":"1.指墓穴。","幽痾":"1.犹沉疴。","幽刻":"1.幽僻峭刻。","幽客":"1.指隐士。 \n2.兰之别名。 \n3.山矾之别名。","幽苦":"1.愁苦。","幽圹":"1.墓穴。","幽况":"1.幽闷的景况。","幽旷":"1.幽深旷远。","幽贶":"1.谓神灵暗中的赐予。","幽阃":"1.犹幽闺。","幽困":"1.犹软禁。","幽濑":"1.深谷中的急流。","幽籁":"1.幽雅的声音。","幽兰":"1.兰花。 \n2.古琴曲名。","幽懒":"1.深居懒散。","幽理":"1.精深的义理。","幽厉":"1.周代昏乱之君幽王与厉王的并称。","幽丽":"1.幽静美丽。","幽辽":"1.僻远。","幽寥":"1.寂静的天空。","幽劣":"1.低劣;微贱。","幽林":"1.幽深茂密的树林。","幽鳞":"1.深水中的鱼。","幽灵":"迷信指鬼神幽灵似的空┬椋将军天挺神武，幽灵所助。","幽囹":"1.牢狱。","幽流":"1.暗流。","幽陇":"1.指坟墓。","幽陋":"1.卑微。亦指卑微而被埋没的人才。 \n2.为自谦之词。","幽陆":"1.谓北方大地。","幽履":"1.犹韬光。隐藏行迹。","幽律":"1.清越的乐律。","幽沦":"1.沉沦;陷没。 \n2.引申指死亡。 \n3.隐蔽﹑幽暗之处。","幽轮":"1.指死者在冥间所乘的车子。","幽霾":"1.阴暗。","幽茂":"1.犹繁茂。","幽没":"1.死亡。","幽美":"1.幽静美丽。 \n2.幽雅美妙。","幽沬":"1.犹幽昧;隐微。","幽昧":"1.昏暗不明。","幽痗":"1.忧痛，悲苦。","幽门":"1.玄妙之门。指精神寄托之所。 \n2.幽深的门户。 \n3.胃与十二指肠相通的部分。中医为七冲门之一。","幽闷":"1.抑郁烦闷。","幽懑":"1.忧闷。","幽蒙":"1.犹幽暗，暗昧。","幽梦":"1.忧愁之梦。 \n2.隐约的梦境。","幽泌":"1.指平静的流水。","幽秘":"1.亦作\"幽秘\"。 \n2.深奥;神秘。 \n3.指神秘之事。","幽密":"1.秘密。 \n2.犹茂盛，茂密。","幽眇":"1.亦作\"幽渺\"。亦作\"幽妙\"。 \n2.精深微妙。","幽渺":"1.见\"幽眇\"。","幽妙":"1.见\"幽眇\"。","幽珉":"1.指墓碑。","幽明":"①指无形和有形的物像仰以观于天文，俯以察于地理，是故知幽明之故。②昼夜；阴阳祭日于坛，祭月于坎，以别幽明，以制上下。③指生与死，阴间与阳间师生恩义，邈若河山，遂成幽明永隔矣｜人神幽明绝，朋好云雨乖。④善恶与贤愚吾贱且辱，不得与考绩幽明之说。","幽冥":"1.玄远;微妙。 \n2.幽暗;黑暗。 \n3.引申为暗地里，暗中。 \n4.暗昧;昏庸。 \n5.幽僻;荒远。 6.地府;阴间。 7.借指死者。","幽铭":"1.墓志铭。","幽溟":"1.指深水。","幽漠":"1.幽静之境。 \n2.指死者。","幽墨":"1.同\"幽默\"。","幽默":"①寂静无声孔静幽默。②有趣或可笑而意味深长充满幽默的笑｜滑稽只逗人笑，而幽默则是让你笑了以后想出许多道理来。","幽暮":"1.昏暗的傍晩。","幽念":"1.静思;深思。","幽女":"1.幽居无偶的女子。","幽哦":"1.低声吟咏。","幽佩":"1.用幽兰连缀而成的佩饰。语本《楚辞·离骚》\"扈江离与薜芷兮，纫秋兰以为佩。\"","幽僻":"1.幽隐，潜藏。 \n2.幽静而偏僻。","幽偏":"1.静僻之处。","幽屏":"1.隐僻之处。","幽朴":"1.谓地位低微，资质朴陋。","幽凄":"1.凄凉;凄厉。","幽栖":"1.幽僻的栖止之处。 \n2.隐居。","幽期":"1.隐逸之期约。 \n2.隐秘或幽雅的约会。 \n3.指男女间的幽会。","幽蹊":"1.犹幽径。","幽奇":"1.指玄妙的哲理。 \n2.幽雅奇妙。","幽契":"1.冥合，默契。 \n2.隐微的心情或契机。","幽阡":"1.墓道。","幽揵":"1.谓深奥的法门。喻佛教经典。","幽潜":"1.隐伏;隐居。 \n2.隐微玄奥的道理。 \n3.深水。","幽谴":"1.冥中的谴责。","幽悄":"1.低微。 \n2.谓幽约微妙。","幽峭":"1.隐僻峻峭。","幽禽":"1.鸣声幽雅的禽鸟。","幽穷":"1.谓幽僻之至。","幽囚":"1.囚禁。","幽求":"1.犹冥索。 \n2.搜求寻访。","幽趋":"1.犹幽趣。幽雅的情趣。","幽阒":"1.静寂。","幽趣":"1.幽雅的趣味。","幽閴":"1.幽静，静寂。","幽泉":"1.幽深隐僻的泉水。 \n2.指阴间地府。 \n3.借指死者。","幽阙":"1.指肾。","幽壤":"1.犹地下;九泉之下。","幽人":"1.幽隐之人;隐士。指幽居之士。","幽柔":"1.低微柔弱。 \n2.幽雅柔美。","幽辱":"1.侮辱。 \n2.指受辱。","幽润":"1.幽洁润泽。","幽若":"1.杜若。香草名。","幽散":"1.隐约地消失或消散。","幽涩":"1.幽寂冷落;冷涩。","幽瑟":"1.幽远而低沉的琴声。","幽杀":"1.囚禁处死。 \n2.阴干。","幽埏":"1.墓道。","幽深":"1.深而幽静。 \n2.引申为遥远;久远。 \n3.幽僻之处。 \n4.指隐士。 \n5.深奥;玄虚。","幽沈":"1.亦作\"幽沉\"。 \n2.犹堙没。 \n3.卑微。 \n4.深藏;隐藏。 \n5.指潜藏在内心的怨恨或不平。 6.隐居。 7.低沉;阴沉。","幽胜":"1.幽静而优美。 \n2.指幽静的胜地。","幽石":"1.犹墓石。","幽士":"1.隐士。","幽事":"1.幽景，胜景。 \n2.雅事。","幽室":"1.幽暗或没有光亮的屋子。 \n2.墓穴。 \n3.石室，山洞。 \n4.指肾脏。","幽菽":"1.亦作\"幽尗\"。 \n2.豆豉。","幽尗":"1.见\"幽菽\"。","幽竪":"1.坟墓。","幽爽":"1.幽雅爽朗。 \n2.犹幽灵。指鬼神。","幽说":"1.精深微妙之说。","幽司":"1.即阴司。阴间的官府。","幽死":"1.囚禁而死。","幽搜":"1.谓探寻山水胜景。","幽叟":"1.指仙翁。 \n2.指隐居的老人。","幽薮":"1.僻静的草泽。","幽素":"1.幽寂，寂静。 \n2.恬淡质朴。 \n3.幽情素心。 \n4.唐科举科目名。","幽愫":"1.隐秘的真情。","幽邃":"1.幽深;深邃。 \n2.指僻远之地。 \n3.深奥。","幽闼":"1.宫中幽深的小门。 \n2.指深闺。","幽台":"1.谓坟墓。","幽探":"1.谓探求幽胜之境。 \n2.深入寻求。","幽堂":"1.幽深的厅堂。 \n2.谓坟墓。","幽天":"1.八方之一。西北方的别称。","幽田":"1.道家谓耳神字幽田，故为耳的代称。","幽通":"1.谓与神灵相遇。 \n2.谓深邃入神。","幽涂":"1.同\"幽途\"。","幽途":"1.佛教语。幽冥之途。指六道轮回中的地狱﹑饿鬼﹑畜生等三恶道。","幽亡":"1.隐没亡失。","幽王":"1.昏昧的帝王。","幽枉":"1.犹冤屈。","幽微":"1.隐微。 \n2.微弱;轻微。","幽委":"1.幽深曲折。","幽蔚":"1.草木茂盛貌。","幽文":"1.隐微玄奥的文辞。 \n2.墓碑铭文。","幽坞":"1.僻静的山坳。","幽寤":"1.犹深悟。","幽穸":"1.墓穴。","幽系":"1.囚禁;拘囚。","幽遐":"1.僻远;深幽。","幽僲":"1.谓仙人。","幽伭":"1.犹幽玄。","幽闲":"1.见\"幽闲(xián)\"。","幽娴":"1.文静雅致。","幽显":"1.犹阴阳。亦指阴间与阳间。","幽险":"1.阴险。 \n2.幽远险阻。 \n3.指险阻僻远之处。","幽飨":"1.祭献鬼神。","幽宵":"1.昏暗的夜晚。","幽心":"1.幽栖之心。","幽欣":"1.内心喜悦貌。","幽馨":"1.犹幽香。喻清高的情操。","幽兴":"1.微奥的旨趣。 \n2.幽雅的兴味。","幽星":"1.夜星。","幽性":"1.谓宁静的心性。","幽夐":"1.幽深;深邃。","幽修":"1.形容声音低微悠长。","幽秀":"1.幽雅秀丽。","幽岫":"1.深山中的岩洞。常为隐者所居之处。","幽虚":"1.见\"幽墟\"。","幽墟":"1.指边远之地。 \n2.指坟墓。","幽绪":"1.郁结于心的深切连绵的思绪。","幽玄":"1.幽深玄妙。 \n2.谓玄虚的释道哲理。 \n3.幽昧，昏暗。 \n4.犹幽冥。阴间。","幽崖":"1.北方的边界。 \n2.幽深的崖岸。","幽涯":"1.见\"幽崖\"。","幽烟":"1.深邃的雾霭。","幽严":"1.幽深静肃。","幽艳":"1.文静秀美。 \n2.引申为美好。","幽燕":"1.古称今河北北部及辽宁一带。唐以前属幽州，战国时属燕国，故名。","幽鴳":"1.传说中的异兽名。","幽扬":"1.低微而悠扬。","幽阳":"1.指初升的太阳。因阳光微弱，故名。唐陈子昂《感遇》诗之一\"微月穻霈幽阳始化升。圆光正东满，阴魄已朝凝。\"一说指月。","幽岟":"1.深邃。","幽妖":"1.隐藏的妖魔。喻奸臣。","幽窅":"1.幽窈，幽深。","幽窈":"1.幽深。 \n2.暗淡。","幽噎":"1.同\"幽咽\"。","幽液":"1.指地下水。","幽噫":"1.深叹声。","幽疑":"1.暗中的怀疑。","幽忆":"1.指深藏心中的思想感情。","幽异":"1.幽深奇异。 \n2.神异。 \n3.谓隐而不显的优异之士。","幽抑":"1.犹郁抑。","幽秇":"1.祭名。古代设坛祈祭星辰之称。","幽悒":"1.犹忧郁。","幽逸":"1.犹隐逸。","幽意":"1.幽深的思绪。 \n2.幽闲的情趣。","幽裔":"1.远僻之地。","幽翳":"1.隐蔽。 \n2.阴暗;阴霾。 \n3.草木繁茂。","幽阴":"1.阴静;幽深。 \n2.阴暗。 \n3.指阴间。 \n4.用以指阴魂。","幽隐":"1.隐晦;隐蔽。 \n2.指隐蔽之处。 \n3.隐居;潜藏。 \n4.指隐居未仕的人。","幽映":"1.隐约的日光。","幽慵":"1.悠闲懒散。","幽忧":"1.过度忧劳;忧伤。","幽幽凄凄":"1.形容伤心之极。","幽悠":"1.犹深远。","幽隅":"1.僻静处。","幽愚":"1.幽暗愚昧。多用为自谦之辞。","幽圄":"1.牢狱。","幽郁":"1.犹忧郁。 \n2.茂盛貌。","幽狱":"1.囚于监狱。 \n2.地狱。","幽冤":"1.深冤。 \n2.指蒙受深冤的人。","幽源":"1.指地狱。","幽圜":"1.谓天。幽，高深;圜，同\"圆\"。古人谓天圆地方。","幽远":"1.深远。 \n2.指幽居草野之士。","幽怨":"1.郁结于心的愁恨。","幽院":"1.幽静的庭院。","幽愿":"1.隐伏在心中的愿望。","幽约":"1.隐约。 \n2.幽雅婉约。 \n3.幽雅的约会。","幽钥":"1.幽雅的乐声。","幽越":"1.幽囚颠越。 \n2.犹悠扬。","幽运":"1.犹冥运。谓命运天定，人不能知。","幽韵":"1.幽深的韵昧。","幽藴":"1.郁结并隐藏在心中的思绪。","幽赞":"1.亦作\"幽赞\"。 \n2.谓暗中受神明佐助。语出《易·说卦》\"昔者圣人之作《易》也，幽赞于神明而生蓍。\"高亨注\"言圣人作《易》，暗中受神明之赞助，故生蓍草，以为占筮之用。\" \n3.谓使隐微难见者明着。","幽赜":"1.幽深精微。","幽仄":"1.微贱;卑陋。 \n2.指隐居之士。","幽轧":"1.象声词。","幽宅":"1.坟墓。","幽障":"1.指边塞上的小城堡。","幽兆":"1.墓穴。","幽折":"1.幽深盘曲。 \n2.隐僻折拗。","幽蛰":"1.冬眠土中的虫类。喻草野或隐退之士。","幽贞":"1.语出《易．履》\"履道坦坦，幽人贞吉。\"后多以\"幽贞\"指隐士。 \n2.指高洁坚贞的节操。","幽真":"1.幽静纯真的情趣。 \n2.幽人隐士的画像。","幽执":"1.囚禁。","幽絷":"1.囚禁。","幽旨":"1.深奥玄妙的旨趣。","幽致":"1.幽雅别致;幽静雅致。 \n2.犹幽趣。 \n3.深奥的道理。","幽滞":"1.隐沦而不用于世。 \n2.指隐沦而未被擢用之士。","幽衷":"1.隐藏于内心的情思。","幽州":"1.亦作\"幽洲\"。古九州之一。 \n2.州名『武帝所置十三部刺史之一。东汉治所在蓟县(今北京城西南)。辖境相当今河北北部及辽宁等地。","幽洲":"1.见\"幽州\"。","幽躅":"1.犹言独自徘徊。","幽篆":"1.墓志铭。","幽拙":"1.愚拙。亦指愚拙的人。","幽姿":"1.幽雅的姿态。","幽子":"1.隐士。","幽宗":"1.犹玄宗。指佛道的深奥义理。","幽踪":"1.谓归隐。","幽阻":"1.奥深险阻。亦指奥深险阻之地。 \n2.幽深偏僻。","幽d":"1.阴沟。参见\"幽?\"。","幽期密约":"幽期相爱男女幽会的时刻。指男女青年定期秘密会面。"}