{"承德":"1.蒙受德泽。","承德市":"在河北省东北部、滦河支流武烈河(热河)沿岸，京承、锦承两铁路终点。为中国历史文化名城。清代称热河、承德，民国时曾为热河省省会。1945年设市，人口396万(1995年)。名胜古迹有避暑山庄和外八庙。","承抵":"1.认罪抵命。","承顶":"1.接受转让。","承蕚":"1.指物件承托的联结部分。","承恩":"1.蒙受恩泽。 \n2.汉台馆名。","承乏":"承继暂时无适当人选的职位敢告不敢，摄官承乏｜予承乏是司郎中。","承风":"1.接受教化。 \n2.谓迎合上官的意图。风，口风。","承奉":"1.承命奉行。 \n2.奉承讨好。","承伏":"1.认罪。","承符吏":"1.唐代州府户曹的小吏。掌文书往返﹑民刑案件的通知诸事。","承福":"1.受福。 \n2.日下有黄气的天象，古称承福。","承辅":"1.辅佐。承，通\"丞\"。《史记．淮南衡山列传论》\"不务遵蕃臣职以承辅天子﹐而专挟邪僻之计。\"《书．冏命》\"旦夕承弼厥辟\"汉孔安国传\"旦夕承辅其君。\"后因以称宰相。","承附":"1.奉承附和。","承构":"1.犹承业。","承顾":"1.承继看管。","承光":"1.汉楼台名。","承荷":"1.犹秉承。","承候":"1.奉侍问候。","承华":"1.汉马监﹑马厩名。 \n2.太子宫门名。 \n3.指太子宫室或太子。","承化":"1.承奉天运，进行教化。","承欢":"①迎合人意，求得欢心那承欢的媚态，令人作呕。②侍奉父母膝下承欢｜承欢乏水浆。","承徽":"1.南朝女官名。","承基":"1.继承基业。","承籍":"1.继承先人的仕籍。","承继":"①继承承继父业｜启贤，能承继禹之道。②过继给无子的叔、伯做儿子。","承家":"1.承继家业。","承间":"1.趁机会。","承浆":"1.穴位名。下唇中央的凹陷处。","承教":"1.接受教令。 \n2.用作谦词，言接受教诲。","承接":"1.交接。 \n2.连接;衔接。 \n3.接受。","承睫":"1.亦作\"承?\"。谓含着眼泪。 \n2.看人眼色，形容逢迎。","承藉":"1.同\"承籍\"。藉，通\"籍\"。 \n2.凭藉。","承局":"1.宋代的低级军职，属殿前司。 \n2.差役的尊称。 \n3.清代皇商在各省的承办人。","承眷":"1.蒙受照顾。","承筐":"1.《诗．小雅．鹿鸣》\"我有嘉宾，鼓瑟吹笙。吹笙鼓簧，承筐是将。\"朱熹集传\"承，奉也。筐，所以盛币帛者也。\"后以\"承筐\"借指欢迎宾客。 \n2.借指馈赠礼品。","承阔":"1.犹承乏。","承揽":"当事人一方为他方完成一定的工作，他方在验收后支付约定的报酬的民事法律行为。其中当事人一方为承揽人，他方为定作人。通常有(物品)加工承揽。","承吏":"1.属吏。承，通\"丞\"。","承领":"1.答理，承认。","承溜":"1.屋檐下承接雨水的槽。亦称\"承落\"。","承流":"1.谓接受和继承良好的风尚传统。","承露":"1.承接甘露。 \n2.即承露盘。 \n3.帻巾，头巾。","承露囊":"1.唐开元十七年，以玄宗生日八月初五为千秋节，百官献承露囊，民间仿制为节日礼品相馈赠。","承露盘":"1.汉武帝迷信神仙，于建章宫筑神明台，立铜仙人舒掌捧铜盘承接甘露，冀饮以延年◇三国魏明帝亦于芳林园置承露盘。","承落":"1.见\"承溜\"。","承买":"1.承受购买。","承蒙":"1.客套语。受到。","承明":"1.古代天子左右路寝称承明，因承接明堂之后，故称。 \n2.即承明庐。","承明庐":"1.汉承明殿旁屋，侍臣值宿所居，称承明庐。又三国魏文帝以建始殿朝群臣，门曰承明，其朝臣止息之所亦称承明庐。《汉书．严助传》\"君厌承明之庐，劳侍从之事，怀故土，出为郡吏。\"颜师古注引张晏曰\"承明庐在石梁阁外，直宿所止曰卢。\"《文选．应璩》\"问我何功德?三入承明庐。\"张铣注\"承明，谒天子待制处也。\"后以入承明庐为入朝或在朝为官的典故。","承命":"1.受命。","承纳":"1.接受。","承逆":"1.犹承迎。","承宁":"1.止息，安定。","承盘":"1.见\"承盘\"。","承破":"1.即承题。","承泣":"1.穴位名。在目下七分目胞陷中，上承瞳子之处。见晋皇甫谧《针灸甲乙经》卷三。 \n2.马目下的旋毛。","承前":"1.遵循前者。 \n2.从前。","承前启后":"承接前面的，开启后面的青年是承前启后的桥梁｜发挥承前启后的作用。","承衾":"1.办丧事。衾，殓尸的包被。","承权":"1.谓权宜除授官员。","承认":"①对事实行为表示确认；同意他承认这是他干的。②即国际承认”。一国认可另一国为主权国家和新的国家机构为合法政府，并愿意与其交往、发展正常关系的外交行为。一般采用相互致函、发照会、发表联合公报、互派外交代表、签订条约等形式来表示。相互承认是建立外交关系的前提。","承嬗离合":"1.继承演变。","承上起下":"1.承接前者，引出后者。","承舍":"1.古时传递公文信件的差役。","承式":"1.效法。","承事":"1.治事;受事。","承侍":"1.侍奉。","承守":"1.谓继承守护先祖的家业。","承受":"1.接受。 \n2.承担;禁受。 \n3.继承。","承授":"1.承继传授。","承衰":"1.承继衰世。","承顺":"1.遵奉顺从。 \n2.敬奉恭顺。","承祀":"1.主持祭祀。指继承帝位。","承嗣":"1.世袭;传代。 \n2.长子。 \n3.指继承为嫡长子。 \n4.即丞司。承，通\"丞\"。","承孙":"1.嫡孙或嫡孙女。","承塌":"1.见\"承搭\"。","承题":"1.申述题意。八股文中之第二股叫\"承题\"。","承天":"1.承奉天道。 \n2.唐代乐舞名。 \n3.唐代宫城南中门叫承天门。","承天命":"1.三国吴乐曲名。韦昭改汉《芳树曲》制。","承祧":"1.承继奉祀祖先的宗庙。 \n2.指承继为后嗣。","承蜩":"1.以竿取蝉。承，通\"拯\"。","承听":"1.听从，接受。","承统":"1.继承帝位。","承头":"1.承当;应承。 \n2.领头。","承托":"1.接受付托。","承望":"1.迎合;逢迎。 \n2.指望。 \n3.料到。","承卫":"1.犹言拱卫。","承务":"1.隋唐官名。《隋书．百官志下》\"废诸司员外郎﹐而每增置一曹郎﹐各为二员……寻又每减一郎﹐置承务郎一人﹐同员外之职。\"后以\"承务\"为地主富豪的通称。","承误":"1.沿袭谬误。","承袭":"1.继承。 \n2.指沿袭。","承檄":"1.秉承檄文之义。谓响应号召。","承先启后":"1.犹承上起下。","承弦":"1.弓弦的副弦。","承想":"1.料想。用于否定词后。","承向":"1.应允。","承泄":"1.容纳排泄。","承兴":"1.乘兴。","承星履草":"1.头戴星光，脚踏草地。形容早出晩归辛勤劳作。","承休":"1.承受美善。","承序":"1.顺序继承。","承绪":"1.承继皇统。","承续":"1.继承延续。","承宣":"1.继承发扬。","承学":"1.学习和继承师说。 \n2.谓从事学问。","承训":"1.接受教令或教诲。","承颜":"1.顺承尊长的颜色。谓侍奉尊长。","承晏墨":"1.南唐墨工李承晏所制墨。","承业":"1.遵命从事。 \n2.继承先代的基业。","承意":"1.秉承意旨;逢迎。","承荫":"1.恩荫授官。","承引":"1.招认罪行。","承印":"1.捧印。 \n2.接受印刷。","承应":"1.指妓女﹑艺人应宫廷或官府之召表演侍奉。","承迎":"1.欢迎;接待。","承影":"1.古代宝剑名。《列子．汤问》记孔周有三浆光﹑承影﹑宵练﹐\"承影﹐将旦昧爽之交﹐日夕昏明之际﹐北面而察之﹐淡淡焉若有物存﹐莫识其状。其所触也﹐窃窃然有声﹐经物而物不疾也。\"","承用":"1.因袭，沿用。","承悦":"1.奉承取悦。","承云":"1.传说为黄帝乐曲。 \n2.衣领。","承允":"1.应允。","承运":"1.秉受天命。 \n2.接受运输。","承载":"1.承受装载。","承泽":"1.蒙受恩泽。 \n2.宝扇。","承招":"1.认罪招供。","承诏":"1.奉诏旨。","承直":"1.见\"承值\"。","承值":"1.亦作\"承直\"。 \n2.当值;侍奉。","承旨":"1.亦作\"承指\"。逢迎意旨。 \n2.接受圣旨。 \n3.官名。唐代翰林院有翰林学士承旨，位在诸学士上。凡大诰令﹑大废置﹑重要政事，皆得专对。宋元仍其制。元赵孟俯曾为此官，世称赵承旨。明废。参阅唐元稹《翰林承旨学士记》。又五代枢密院有枢密院承旨﹑副承旨;宋代枢密院有都承旨﹑副承旨。初用武臣，后参用文臣。参阅《文献通考．职官十二》。","承指":"1.见\"承旨\"。","承志":"1.迎合意旨。 \n2.继承大志。","承制":"1.谓秉承皇帝旨意而便宜行事。 \n2.称开府承制之官。","承贽":"1.奉上礼品。","承重":"1.指承受宗庙与丧祭的重任。封建宗法制度，其人及父俱系嫡长，而父先死，则祖父母丧亡时，其人称承重孙。如祖父及父均先死，于曾祖父母丧亡时，称承重曾孙。遇有这类丧事都称承重。 \n2.承受重量。","承转":"1.收到上级公文转交下级，或收到下级公文转送上级。","承总":"1.总揽。","承做":"1.接受加工。","承安":"1.犹承平。","承办":"1.接受办理。","承包经营":"生产资料所有者将企业或生产资料的经营权委托给承包人经营。在我国是经济体制改革中的一项措施。一般通过招标选择承包人，双方权利义务在合同中予以规定。这种经营方式，不改变所有制性质。","承弼":"1.承命辅佐。","承弊":"1.承接衰世。","承宾":"1.接待宾客。","承摈":"1.佐傧。承，通\"丞\"。","承禀":"1.禀告。 \n2.奉命。","承差":"1.即承局。","承禅":"1.接受禅让。","承尘":"①承受尘土，也指古代承接尘土的帐子或小帐幕。②藻井，天花板默投金于承尘上，后葺理屋宇，乃得之｜彩饰承尘。","承承":"1.谓代代承继。","承宠":"1.承受恩宠。","承从":"1.听从;顺从。","承搭":"1.亦作\"承塌\"。 \n2.应承。","承答":"1.对答。","承担":"1.担负;担当。","承当":"1.承担，担当。","承欢膝下":"承欢旧指侍奉父母；膝下子女幼时依于父母膝下，故表示幼年。旧指侍奉父母。","承平盛世":"承平太平。太平、兴盛的时代。","承上启下":"承接上面的，引起下面的。多用在写文章方面。","承天之祜":"承蒙受；祜福。蒙受老天的赐福。","承天之佑":"承受；佑保佑。蒙受老天的保佑。","承天之祐":"承受；祐保佑。蒙受老天的保祐。","承颜候色":"看人脸色行事，不敢有不同意见。"}