{"拟程":"1.科举制度中主考官拟作的示范文章。又称拟墨。","拟斥":"1.谓仿效帝王制度。","拟待":"1.犹打算。","拟抵":"1.犹抵命。","拟订":"1.草拟。","拟定":"1.一定。 \n2.决定。 \n3.起草制定。","拟度":"1.揣度;推测。","拟法":"1.效法。","拟范":"1.效法。","拟非其伦":"1.谓比拟不当。语本《礼记．曲礼下》\"拟人必于其伦。\"","拟稿":"1.起草文稿。","拟古":"1.诗文仿效古人的风格形式。如汉扬雄拟《易》作《太玄》﹐拟《论语》作《法言》﹐以及《文选》中的\"杂拟\"等◇成为诗体之一。晋陆机﹑南朝宋鲍照等皆有《拟古》诗。","拟规画圆":"1.谓依样模仿。","拟捍":"1.犹防御。","拟话本":"模拟话本形式创作的小说。今多指明代文人模拟宋元话本所写的白话短篇小说，如冯梦龙的三言”、凌c049３醯亩拍”等。","拟迹":"1.亦作\"拟迹\"。 \n2.仿效。 \n3.揣度足迹。","拟经":"1.汉扬雄仿《易》作《太玄》﹐仿《论语》作《法言》﹐后人谓之\"拟经\"。","拟寇":"1.犹御寇。","拟伦":"1.比拟;伦比。","拟论":"1.指拟立为太子之说。 \n2.科学上有待证明的假设。","拟貌":"1.摹拟描摹。","拟墨":"1.即拟程。","拟票":"1.明清时﹐各处奏本送达内阁后﹐由阁员用墨笔预拟批答于浮票﹐再送呈皇帝朱批﹐称为拟票﹐也称票拟。","拟人":"把事物人格化的修辞格。例如童话里的动物会像人一样思考、说话。","拟容":"1.谓形貌上的比拟。","拟声词":"也称象声词”。摹拟自然声音的词。如哗啦、轰隆、叮咚。","拟圣":"1.比拟圣人。 \n2.仿效圣人。","拟疏":"1.奏疏的草稿。","拟水":"1.古代祭祀仪式中模拟盥洗的动作。","拟死":"1.定为死刑。 \n2.指某些昆虫的假死。因受外界惊动或袭击而呈半死状态﹐静伏不动﹐或跌落地面如死物﹐借以避敌。","拟题":"1.应试举子揣度命题。 \n2.拟定题目。","拟托":"1.见\"拟托\"。","拟物":"1.修辞方式之一。把人拟作物或把甲物拟作乙物。","拟宪":"1.效法。","拟想":"1.犹设想。","拟象":"1.模仿其状。","拟效":"1.仿效。","拟行路难":"乐府组诗名。南朝宋鲍照作。共十八首。主要抒发对人生艰难的感慨，表达出身寒门的士人在仕途中的坎坷和痛苦。也有描写游子和思妇之作。大多感情强烈，语言遒劲，辞藻华丽。有五言、七言及杂言句。","拟学":"1.犹仿效。","拟盐":"1.南朝宋刘义庆《世说新语．言语》\"谢太傅寒雪日内集﹐与儿女讲论文义。俄而雪骤﹐公欣然曰'白雪纷纷何所似？'兄子胡儿曰'撒盐空中差可拟。'兄女曰'未若柳絮因风起。'公大笑乐。\"后以\"拟盐\"指咏雪。","拟仪":"1.模仿其法度;仿效。","拟用":"1.拟定使用。 \n2.备用。","拟谕":"1.见\"拟喻\"。","拟喻":"1.亦作\"拟谕\"。 \n2.打比方。","拟则":"1.效法;模仿。","拟正":"1.试任或代理官员改为正式任命。","拟制":"1.比拟其规模制度。 \n2.草拟制订。","拟质":"1.犹比拟。","拟肘":"1.指袁绍对曹操举印向肘事。","拟主":"1.越分比于君主。","拟注":"1.宋代官制。应试入选者﹐由吏部注名于册﹐经考询后拟定授官﹐称为拟注。","拟柱体":"所有顶点都在两个平行平面内的多面体。两个互相平行的面称为拟柱体的底面，其余的面称为拟柱体的侧面，两个底面之间的距离称为拟柱体的高。设拟柱体的上、下底面和中截面面积分别为q１、q２、q０，高为h，则其体积v=16h(q1+4q0+q2)。","拟踪":"1.谓打算达到。","拟奏":"1.起草奏章;准备奏呈。","拟足":"1.揣度脚步。 \n2.谓投足。","拟罪":"1.定罪。","拟作":"1.摹仿别人的风格或假托其口吻而写的作品。亦谓摹仿别人进行写作。","拟于不伦":"用不能相比的人或事物来比方。"}