{"旌褒":"1.表彰。","旌贲":"1.褒美。","旌币":"1.亦作\"旍币\"。 \n2.招求贤士时所馈赠的币帛。","旌表":"封建统治者用立牌坊或挂匾额等表扬遵守封建礼教的人。","旌别":"识别；甄别旌别善恶。","旌帛":"1.古时礼聘贤士所送的束帛。","旌车":"1.即旌蒲。","旌崇":"1.表彰。","旌宠":"1.表彰尊崇。","旌大":"1.表彰光大。","旌纛":"1.大旗。亦泛指旗帜。 \n2.犹尊驾。","旌德":"1.表彰有德之人。","旌典":"1.表彰贞烈的匾额。","旌毦":"1.旌旗上的羽饰。","旌幡":"1.见\"旌旛\"。","旌旛":"1.亦作\"旌幡\"。 \n2.泛指旗帜。","旌繁":"1.车马的饰物。旌﹐车的旗饰;繁﹐马缨。","旌盖":"1.旌旗和车盖。","旌干":"1.见\"旌竿\"。","旌竿":"1.亦作\"旌干\"。 \n2.旗竿。","旌弓":"1.亦作\"旍弓\"。 \n2.征聘贤士的旌旗和弓。语本《孟子．万章下》\"﹝招﹞大夫以旌。\"","旌鼓":"1.古代用以规谏帝王的旌旗和谏鼓。语本《大戴礼记．保傅》\"有进善之旍……有敢谏之鼓。\" \n2.旌旗和战鼓。","旌罕":"1.旌旗”﹐旗名﹐帝王所用。","旌麾":"①帅旗。用羽装饰的军旗，用以指挥军队破敌军夺其旌麾。②借指军队或军旅之事奉辞伐罪，旌麾南指。","旌戟":"1.旌旗与棨戟。用作官员出行的仪仗。 \n2.借指贵官。","旌嘉":"1.褒扬嘉奖。","旌甲":"1.旌旗与铠甲。","旌简":"1.表彰盐。","旌奬":"1.表彰奖赏。","旌节花":"1.花名。叶卵形﹐有锯齿。春夏之交开花。花小﹐色黄﹐成穗状的总状花序。浆果小球形﹐成串﹐可观赏。","旌捷旗":"1.告捷的旗子。","旌举":"1.表彰举荐。","旌旝":"1.泛指旗帜。","旌劳":"1.褒奖慰劳。","旌旒":"1.亦作\"旌斿\"。 \n2.旌旗。","旌録":"1.表彰叙录。","旌闾":"1.旌表门闾。旧时朝廷对所谓忠孝节义的人﹐赐给匾额﹐挂于门廷之上﹐或树立牌坊﹐以示表彰。","旌旄":"1.军中用以指挥的旗子。 \n2.泛指旗帜。 \n3.借指官兵。","旌门":"1.古代帝王出行﹐张帷幕为行宫﹐宫前树旌旗为门﹐称旌门。 \n2.犹旌闾。","旌密":"1.精密。旌﹐通\"精\"。","旌铭":"1.旧时灵柩前书写死者姓名官衔的旗幡。又称铭旌。","旌命":"1.表彰征召。 \n2.招聘贤士的命令;表彰的命令。","旌木":"1.古代用以规谏帝王的旌旗和谤木。语本《大戴礼记．保傅》\"有进善之旍﹐有诽谤之木。\"卢辩注\"［旍(旌)﹐］尧置之﹐令进善者立于旍下也。﹝木﹐﹞尧置之﹐使书政之樖б病\"","旌斾":"1.亦作\"旌旆\"。 \n2.旗帜。 \n3.犹尊驾﹑大驾。多用于官员。 \n4.借指军旅。","旌旆":"1.见\"旌斾\"。","旌蒲":"1.古时征聘贤士所用的旌帛和蒲车。","旌棨":"1.旌旗与棨戟。借指贵官。","旌劝":"1.表彰奖励。","旌儒庙":"1.庙名。唐玄宗时建。故址在相传秦始皇坑儒处﹐即今陕西省临潼县东南。","旌色":"1.旌旗的色彩。","旌善":"1.表彰美善。","旌赏":"1.表彰奖赏。","旌尚":"1.表彰。","旌祀":"1.表彰与祭祀。","旌帷":"1.铭旌与帷帐。均为丧仪用物。","旌夏":"1.古时乐舞所用的大旗。","旌贤":"1.亦作\"旍贤\"。 \n2.表彰贤人。","旌显":"1.旌表。","旌孝":"1.表彰孝行。","旌信":"1.表明诚意。","旌叙":"1.表扬而录用为官。","旌恤":"1.亦作\"旌恤\"。 \n2.表彰死者并抚恤其遗属。","旌轩":"1.建有旌节的车。","旌延":"1.表彰聘请。","旌扬":"1.表扬。","旌阳宅":"1.相传为晋许逊炼丹成仙处。亦借称修炼成仙之所。","旌异":"1.旌表;褒奖。","旌枻":"1.见\"旌栧\"。","旌栧":"1.树在船上的旌旗。","旌引":"1.表扬荐引。","旌庸":"1.表彰有功的人。","旌斿":"1.见\"旌旒\"。","旌舆":"1.招贤用的车子。","旌旟":"1.泛指旗帜。","旌羽":"1.旌旗。因有羽饰﹐故称。","旌钺":"1.旌旗与斧钺。 \n2.喻权柄。","旌旃":"1.泛指旗帜。","旌招":"1.以旌招之。谓征召贤士。语本《孟子．万章下》\"敢问招虞人何以？曰'以皮冠。庶人以旃﹐士以旗。大夫以旌。'\"","旌旐":"1.旌旗。 \n2.指铭旌﹐导引灵柩的魂幡。","旌甄":"1.表彰盐。","旌直":"1.表彰忠直。","旌帜":"1.旗帜。","旌智":"1.发挥智慧。","旌忠":"1.表彰忠节。","旌擢":"1.表彰提拔。","旌旗蔽日":"旌旗旗帜的通称，这里特指战旗。战旗遮住了日光。形容军队数量众多，阵容雄壮整齐。","旌旗卷舒":"舒展开。战旗随风飘动，有时卷起，有时展开。比喻战事持续。"}