{"狎爱":"1.犹宠爱。","狎逼":"1.亲近狎戏。","狎比":"1.亲近;亲昵。","狎博":"1.无节制地赌博。","狎处":"1.亲密相处。","狎从":"1.亲密相从。","狎道":"1.习道。","狎敌":"1.轻敌。","狎法":"1.亵渎法制。","狎妓":"1.旧指玩弄妓女。","狎近":"1.亲近。","狎竞":"1.迭起争竞。","狎客":"1.陪伴权贵游乐的人。 \n2.旧称嫖客。 \n3.茉莉的别名。","狎猎":"1.众饰缤纷貌。 \n2.重叠接续貌。","狎躐":"1.连续不断貌。","狎鬣":"1.接连不断貌。","狎慢":"1.亲热轻慢。","狎密":"1.犹亲密。","狎妮":"1.亲近。","狎昵":"1.亦作\"狎昵\"。 \n2.亲近;亲昵。 \n3.指男女淫猥苟合。","狎溺":"1.过分宠爱。","狎弄":"1.亲近戏弄。","狎鸥":"1.《列子．黄帝》\"海上之人有好沤鸟者，每旦之海上，从沤鸟游，沤鸟之至者百住而不止。其父曰'吾闻沤鸟皆从汝游，汝取来，吾玩之。'明日之海上，沤鸟舞而不下也。\"沤，同\"鸥\"◇以\"狎鸥\"指隐逸。","狎帢":"1.犹匼匝。环绕貌。","狎恰":"1.密集﹑拥挤貌。","狎扰":"1.谓亲近嬉闹。","狎赏":"1.谓亲昵﹑不拘礼节的宴集。","狎世":"1.随附世俗。","狎视":"1.轻视;蔑视。","狎兽":"1.驯顺之兽。","狎书":"1.行书之一体。","狎熟":"1.亲昵﹑熟习。","狎俗":"1.迎合流俗。","狎徒":"1.指陪主人嬉戏凑趣的人。","狎玩":"1.见\"狎耫\"。","狎猥":"1.谓轻浮猥陋。","狎侮":"1.轻慢侮弄。","狎息":"1.狎游﹑一同寝处。","狎习":"1.亲近熟习。","狎戏":"1.戏耍;狎昵。","狎黠":"1.谓习于弄巧。","狎笑":"1.亲昵嬉笑。","狎邪":"1.谓行为放荡，品行不端。 \n2.狭斜。小街;曲巷。借指妓院或妓女。","狎邪游":"1.指狎妓。","狎亵":"1.犹放荡，淫秽。 \n2.亵渎﹐轻慢。 \n3.指亲密嬉戏。","狎媟":"1.亲昵而近于放荡。","狎信":"1.犹亲信。","狎兴":"1.狎游的兴致。","狎谑":"1.戏谑，玩笑。","狎筵":"1.谓不拘礼法的宴饮。","狎宴":"1.亲昵﹑不拘礼节的饮宴。","狎燕":"1.见\"狎宴\"。","狎异":"1.谓亲近异常。","狎饮":"1.放纵地饮酒。","狎游":"1.亦作\"狎游\"。 \n2.指狎邪游。 \n3.亲昵嬉游。","狎语":"1.猥亵的话。 \n2.戏言。","狎耫":"1.亦作\"狎玩\"。 \n2.接近﹑戏弄。语出《左传．昭公二十年》\"水懦弱，民狎而玩之，则多死焉。\"","狎至":"1.接连而来。","狎雉驯童":"1.汉鲁恭宰中牟，以德化民。时郡国螟蝗伤稼，独不入其境;有母雉将雏过童子旁，童子仁而不捕。事见《后汉书．鲁恭传》◇因以\"狎雉驯童\"誉人政绩。","狎主":"1.交替主持。"}