{"狡暴":"1.指狡猾凶暴之人。","狡愎":"1.蛮横执拗。","狡宾":"1.狡客。","狡虫":"1.凶害之虫。 \n2.犹狡兽。","狡妒":"1.猜疑妒忌。","狡诡":"1.狡猾诡诈。","狡悍":"1.狡猾凶悍。 \n2.谓壮健勇武。","狡好":"1.容貌秀丽。狡，通\"姣\"。","狡很":"1.见\"狡狠\"。","狡狠":"1.亦作\"狡很\"。 \n2.狡诈狠毒。","狡横":"1.狡诈蛮横。","狡猾":"诡计多端，不可信任。也作狡滑。","狡慧":"1.狡猾机敏。","狡惑":"1.淆乱。","狡计":"狡猾的计谋。","狡讦":"1.犹诋毁。","狡捷":"1.灵活敏捷。","狡竞":"1.犹好胜。","狡狙":"1.狡猾奸诈。","狡抗":"1.狡顽违抗。","狡口":"1.巧诈之口。谓善辩。","狡赖":"狡辩抵赖百般～。","狡吏":"1.狡猾的官吏。","狡乱":"1.为害作乱。","狡谋":"1.狡诈的计谋。","狡扇":"1.狡诈煽惑。","狡兽":"1.矫健凶猛的野兽。","狡笇":"1.见\"狡筭\"。","狡筭":"1.狡猾奸诈。 \n2.亦作\"狡笇\"。犹虚张。","狡慝":"1.奸邪。","狡童":"1.姣美的少年。 \n2.《诗．郑风》有《狡童》篇，讥刺公子忽◇以\"狡童\"借指壮狡昏乱的国君。亦作\"狡僮\"。 \n3.指霸占一方的割据者。 \n4.未成年的童仆。","狡童之歌":"1.指商代箕子作的《麦秀歌》。","狡兔得而猎犬烹":"1.比喻国君得了天下，就杀害谋士功臣。","狡兔死，良狗烹":"1.见\"狡兔得而猎犬烹\"。","狡妄":"1.狡猾狂妄。","狡伪":"1.狡诈虚伪。","狡黠":"〈书〉狡诈。","狡险":"1.狡诈阴险。","狡心":"1.狡猾之心。","狡幸":"1.犹狡狠。","狡性":"1.谓猜疑的心性。","狡獝":"1.谓狡猾多诈。","狡穴":"1.指狡兔之穴。","狡焉思逞":"1.见\"狡焉思启\"。","狡焉思肆":"1.见\"狡焉思启\"。","狡勇":"1.狡诈勇悍。","狡兔三窟":"窟洞穴。狡猾的兔子准备好几个藏身的窝。比喻隐蔽的地方或方法多。","狡兔三穴":"比喻隐蔽的地方或方法多。同狡兔三窟”。","狡兔死，良犬烹":"比喻给统治者效劳的人事成后被抛弃或杀掉。同狡兔死，良狗烹”。","狡焉思启":"指怀贪诈之心图谋侵人之国。"}