{"莽苍":"①空旷无边的样子莽苍大地｜莽苍郊野。②原野目穷莽苍。","莽苍苍":"1.一望无际。 \n2.空阔;迷茫。","莽草":"1.植物名。一种有毒植物。又称水莽草。","莽大夫":"1.指汉代扬雄。扬雄本仕汉朝，王莽称帝时，仕莽为大夫。 \n2.比喻变节者。","莽宕":"1.广阔貌。","莽荡":"1.辽阔无际。 \n2.迂阔;迂远不切实际。 \n3.激荡;震撼。","莽荡荡":"1.辽阔旷远貌。","莽夺":"1.强抢。","莽古歹":"1.蒙古语。指小番。","莽汉":"1.粗鲁冒失的男子。","莽沆":"1.水广大貌。","莽浪":"1.虚诞。","莽卤":"1.粗疏;马虎。 \n2.凝不明。","莽鲁":"1.草率;马虎。","莽茫":"1.犹茫茫。","莽莽":"①草木茂盛的样子草木莽莽。②茫无际涯的样子莽莽万重山。","莽莽苍苍":"1.鲁莽冒失。 \n2.无边无际。 \n3.荒凉貌。","莽莽漠漠":"1.模凝糊。","莽沕":"1.高低不平貌。","莽眇":"1.深远;高远。 \n2.犹迷茫。","莽渺":"1.邈远貌。","莽然":"1.草木茂盛貌。 \n2.广大貌;众多貌。 \n3.犹猛然。","莽式":"1.满族歌舞名。","莽跳":"1.乱钻门路。","莽瀥":"1.辽阔广远貌。","莽泱":"1.辽阔广远貌。","莽壮":"1.卤莽。 \n2.形容声音﹑气力粗壮有力。","莽撞":"粗疏冒失行为莽撞｜莽撞的冒失鬼。"}