{"赊迟":"1.延缓;拖延。","赊促":"1.远近;缓急;长短。","赊贷":"1.赊欠;借贷。","赊购":"1.用欠账的方式购买。","赊荷":"1.赊欠和负债。","赊缓":"1.迟缓;缓慢。","赊借":"1.犹赊贷。","赊老":"1.犹却老。","赊买":"1.欠账购买。 \n2.谓不需付出代价而占有。","赊卖":"1.买卖货物时，卖方延期收款。","赊弥":"1.古国名。","赊僻":"1.偏远。","赊钱":"1.所欠的货款。","赊欠":"1.买卖货物时买方延期交款，或卖方延期收款。","赊请":"1.向官府借贷钱物。","赊券":"1.欠账的字据。","赊市":"1.赊买，购物不付现钱。","赊贳":"1.亦作\"賖贳\"。 \n2.犹赊贷。","赊死":"1.缓死。","赊头":"1.指欠账的期限。","赊望":"1.亦作\"賖望\"。 \n2.过高的愿望。","赊销":"1.用赊欠的方式销售。","赊刑":"1.谓刑法松弛。","赊遥":"1.久远，遥远。","赊远":"1.久远;遥远。","赊愿":"1.宿愿。","赊帐":"1.亦作\"赊账\"。 \n2.把买卖的货款记在帐上延期收﹑付。","赊账":"1.见\"赊帐\"。"}