{"踢踧":"1.跳跃貌。 \n2.象声词。","踢达":"1.错过。","踢荡":"1.挥霍，糟蹋。","踢韐":"1.踢毽子。","踢脚":"1.跺脚。人在愤怒或焦急时的动作。","踢里拖落":"1.象声词。","踢良秃栾":"1.飘转貌。","踢木":"1.古代杂耍之一。","踢弄":"1.古代百戏之一。 \n2.称在百戏中扮演脚色或表演节目。 \n3.脚踢手弄;摆弄。 \n4.踢，用脚击物。 \n5.践踏，摧残。","踢皮球":"1.比喻工作不负责任，互相扯皮推委。","踢气球":"1.亦作\"踢气球\"。 \n2.古代的足球运动。球以皮革制成，球内实以毛发，内中鼓气。原为练武之用，后亦作为杂技﹑游戏项目。","踢枪弄棒":"1.犹言使枪弄棒。","踢磬":"1.杂技的一种。演员仰卧，双脚上举摆弄石磬作表演。","踢球":"1.亦作\"踢球\"。蹴鞠。古代的一种足球运动。其方式与设备器物历有变更。唐代为在场地上插两根长竹，顶端结网。踢球人分为两队，踢球过网，以角胜负。相传为古代军中士兵习武之戏演变而来。唐宋以后亦指踢皮球或在野地上用足尖用力压球使其转动而前。球多为石质，可以两枚，踢时以球撞球。 \n2.现代指踢足球。","踢竖":"1.见\"踢竖\"。","踢踏":"1.踏。 \n2.乱用财物;糟蹋。","踢蹋":"1.糟蹋。 \n2.象声词。","踢腾":"1.挥霍，糟蹋。 \n2.又踢又蹬。","踢踢绊绊":"1.行走跌撞貌。","踢秃":"1.象声词。脚步声。","踢脱":"1.除籍。旧时指妓女从良。","踢胸":"1.一种系在马胸前的华丽的装饰品，常以此显示其主人地位的尊贵。","踢圆":"1.踢球。","踢陟":"1.方言。险峻高耸貌。","踢天弄井":"能上天，能入地。比喻本领极大。也形容顽皮到极点。。"}