{"隽拔":"1.卓异出众。 \n2.俊逸超特。","隽才":"1.亦作\"隽材\"。 \n2.才智出众的人﹔出众的才智。隽﹐通\"俊\"。","隽材":"1.见\"隽才\"。","隽乘":"1.指骏马。","隽楚":"1.杰出人物。","隽词":"1.犹隽语。","隽脆":"1.优美爽利。","隽德":"1.才德杰出的人。","隽发":"1.亦作\"隽发\"。英俊豪迈。 \n2.谓才华﹑情性﹑文采等充分表露。","隽辅":"1.杰出的辅佐者。","隽功":"1.突出的功勋。 \n2.功勋特出者。","隽轨":"1.喻特出的典范。","隽豪":"1.亦作\"隽豪\"。 \n2.豪俊之士。","隽杰":"1.出众的人才。","隽洁":"1.亦作\"隽洁\"。 \n2.优美简洁。","隽句":"1.意味深长的语句。","隽絶":"1.卓异绝伦。","隽蹶":"1.犹胜败。","隽客":"1.橘花的雅称。","隽快":"1.健壮敏捷。 \n2.优美畅达。","隽朗":"1.俊秀明悟。","隽老":"1.才德杰出的耆老。","隽李":"1.地名。在今浙江省嘉兴市西南七十里。","隽良":"1.指优秀杰出的人才。","隽流":"1.风雅的人或事。","隽迈":"1.英俊豪迈。","隽髦":"1.杰出之士。","隽茂":"1.才智出众的人。","隽美":"1.亦作\"隽美\"。 \n2.犹优美。","隽妙":"1.亦作\"隽妙\"。 \n2.隽永美妙。","隽敏":"1.俊秀敏快。","隽品":"1.亦作\"隽品\"。 \n2.优良的品级﹔精品。","隽气":"1.英俊的气概。","隽器":"1.杰出的人才。","隽巧":"1.亦作\"隽巧\"。 \n2.犹秀美﹔巧妙。","隽人":"1.杰出人物。隽﹐通\"俊\"。","隽赡":"1.谓文才俊美丰赡。","隽声":"1.犹美誉。","隽士":"1.才智出众的人。隽﹐通\"俊\"。 \n2.唐代科举中的一科。","隽爽":"1.优美明快。","隽俗":"1.卓异脱俗。","隽谈":"1.美谈﹐佳话。","隽婉":"1.精美婉约。","隽望":"1.犹美誉。","隽伟":"1.亦作\"隽伟\"。 \n2.优美而宏伟。","隽味":"1.美味。 \n2.深长的意味。","隽蔚":"1.谓意味深长﹐富有文采。","隽武":"1.超人的武勇。","隽贤":"1.指才德杰出的人。","隽秀":"1.亦作\"隽秀\"。 \n2.优异出众。 \n3.指优异出众者。 \n4.清雅秀丽。","隽雅":"1.优美典雅。","隽彦":"1.才德特出之士。","隽觾":"1.鸟名。","隽异":"1.见\"隽异\"。","隽逸":"1.亦作\"隽逸\"。 \n2.俊秀飘逸﹔超群拔俗。 \n3.才智俊秀不凡之士。","隽英":"1.杰出人物。","隽游":"1.犹良友。","隽语":"隽永的话语～箴言。","隽誉":"1.犹美誉。","隽远":"1.亦作\"隽远\"。 \n2.犹深刻。","隽造":"1.才智出众的人。语本《礼记．王制》﹕\"司徒论选士之秀者而升之学﹐曰俊士。升于司徒者不征于乡﹐升于学者不征于司徒﹐曰造士。\"","隽哲":"1.聪明睿智。 \n2.指聪明睿智者。","隽乿":"1.亦作\"隽乿\"。 \n2.才德超卓的人。隽﹐通\"俊\"。 \n3.指才德超卓。","隽壮":"1.优美雄健。","隽资":"1.出众的天资。"}